Metadata-Version: 1.0
Name: feishu-plain-message
Version: 1.0.0
Summary: Send Plain Message To Feishu
Home-page: https://github.com/yinhuanyi/feishu-plain-message
Author: Robby
Author-email: yinhuanyicn@gmail.com
License: MIT
Platform: UNKNOWN
